raystreaming/config.py
raystreaming/function.py
raystreaming/__init__.py
raystreaming/message.py
raystreaming/_streaming.so
raystreaming/operator.py
raystreaming/context.py
raystreaming/datastream.py
raystreaming/partition.py
raystreaming/collector.py
raystreaming/runtime/__init__.py
raystreaming/runtime/remote_call.py
raystreaming/runtime/graph.py
raystreaming/runtime/task.py
raystreaming/runtime/command.py
raystreaming/runtime/context_backend.py
raystreaming/runtime/gateway_client.py
raystreaming/runtime/processor.py
raystreaming/runtime/failover.py
raystreaming/runtime/transfer.py
raystreaming/runtime/serialization.py
raystreaming/runtime/worker.py
raystreaming/generated/__init__.py
raystreaming/generated/streaming_pb2.py
raystreaming/generated/remote_call_pb2.py
raystreaming/tests/__init__.py
raystreaming/tests/test_stream.py
raystreaming/tests/test_direct_transfer.py
raystreaming/tests/test_word_count.py
raystreaming/tests/test_failover.py
raystreaming/tests/test_union_stream.py
raystreaming/tests/test_hybrid_stream.py
raystreaming-0.0.1.dist-info/WHEEL
raystreaming-0.0.1.dist-info/top_level.txt
raystreaming-0.0.1.dist-info/RECORD
raystreaming-0.0.1.dist-info/METADATA
